<!-- Istanze Art. 16 Online -->

<PUBLISHER name="ASScaricoIstanzePagePublisher">
    <RENDERING channel="HTTP" type="JSP" mode="FORWARD">
      <RESOURCES>
        <item prog="0" resource="/jsp/ido/asOnline/scaricoIstanze.jsp"/>
      </RESOURCES>
    </RENDERING>
</PUBLISHER>

<PUBLISHER name="ASDocumentiIstanzaPagePublisher">
    <RENDERING channel="HTTP" type="JSP" mode="FORWARD">
      <RESOURCES>
        <item prog="0" resource="/jsp/ido/asOnline/documentiIstanza.jsp"/>
      </RESOURCES>
    </RENDERING>
</PUBLISHER>

<PUBLISHER name="DettDocumentoIstanzaPagePublisher">
    <RENDERING channel="HTTP" type="JSP" mode="FORWARD">
      <RESOURCES>
        <item prog="0" resource="/jsp/ido/asOnline/dettaglioDocIstanza.jsp"/>
      </RESOURCES>
    </RENDERING>
</PUBLISHER>

<PUBLISHER name="StoricoScartiIseePagePublisher">
    <RENDERING channel="HTTP" type="JSP" mode="FORWARD">
      <RESOURCES>
        <item prog="0" resource="/jsp/ido/asOnline/storicoScartiIsee.jsp"/>
      </RESOURCES>
    </RENDERING>
</PUBLISHER>

<PUBLISHER name="DettaglioScaricoIstanzePagePublisher">
    <RENDERING channel="HTTP" type="JSP" mode="FORWARD">
      <RESOURCES>
        <item prog="0" resource="/jsp/ido/asOnline/listaCandidatureIstanza.jsp"/>
      </RESOURCES>
    </RENDERING>
</PUBLISHER>

<PUBLISHER name="DettaglioCandidaturaPagePublisher">
    <RENDERING channel="HTTP" type="JSP" mode="FORWARD">
      <RESOURCES>
        <item prog="0" resource="/jsp/ido/asOnline/dettaglioCandidatura.jsp"/>
      </RESOURCES>
    </RENDERING>
</PUBLISHER>

<PUBLISHER name="DettaglioScaricoIstanzeStoPagePublisher">
    <RENDERING channel="HTTP" type="JSP" mode="FORWARD">
      <RESOURCES>
        <item prog="0" resource="/jsp/ido/asOnline/listaCandidatureIstanzaStorico.jsp"/>
      </RESOURCES>
    </RENDERING>
</PUBLISHER>