<PUBLISHER name="ConsultaCOPagePub">
	<RENDERING channel="HTTP" mode="FORWARD" type="JSP">
		<RESOURCES>
			<ITEM prog="0" resource="/jsp/movimentiCoLav/consultaCo.jsp"/>
		</RESOURCES>
	</RENDERING>
</PUBLISHER>
<PUBLISHER name="StoricoCOPagePub">
	<RENDERING channel="HTTP" mode="FORWARD" type="JSP">
		<RESOURCES>
			<ITEM prog="0" resource="/jsp/movimentiCoLav/storicoCo.jsp"/>
		</RESOURCES>
	</RENDERING>
</PUBLISHER>
<PUBLISHER name="RapportiAttiviCOPagePub">
	<RENDERING channel="HTTP" mode="FORWARD" type="JSP">
		<RESOURCES>
			<ITEM prog="0" resource="/jsp/movimentiCoLav/rapportiAttiviCo.jsp"/>
		</RESOURCES>
	</RENDERING>
</PUBLISHER>
<!-- REDDITO DI CITTADINANZA -->
<PUBLISHER name="RicercaNotificheRDCPagePub">
	<RENDERING channel="HTTP" mode="FORWARD" type="JSP">
		<RESOURCES>
			<ITEM prog="0" resource="/jsp/notificheRDC/ricercaNotificheRDC.jsp"/>
		</RESOURCES>
	</RENDERING>
</PUBLISHER>
<PUBLISHER name="ListaNotificheRDCPagePub">
	<RENDERING channel="HTTP" mode="FORWARD" type="JSP">
		<RESOURCES>
			<ITEM prog="0" resource="/jsp/notificheRDC/listaNotificheRDC.jsp"/>
		</RESOURCES>
	</RENDERING>
</PUBLISHER>
<PUBLISHER name="NotificaRDCPagePub">
	<RENDERING channel="HTTP" mode="FORWARD" type="JSP">
		<RESOURCES>
			<ITEM prog="0" resource="/jsp/notificheRDC/notificaRDC.jsp"/>
		</RESOURCES>
	</RENDERING>
</PUBLISHER>
<PUBLISHER name="LinguettaNotificheRDCPagePub">
	<RENDERING channel="HTTP" mode="FORWARD" type="JSP">
		<RESOURCES>
			<ITEM prog="0" resource="/jsp/notificheRDC/notificheLavoratoreRDC.jsp"/>
		</RESOURCES>
	</RENDERING>
</PUBLISHER>
<PUBLISHER name="CruscottoRDCPagePub">
	<RENDERING channel="HTTP" mode="FORWARD" type="JSP">
		<RESOURCES>
			<ITEM prog="0" resource="/jsp/notificheRDC/cruscottoRDC.jsp"/>
		</RESOURCES>
	</RENDERING>
</PUBLISHER>
<PUBLISHER name="EsitoNucleoRDCPagePub">
	<RENDERING channel="HTTP" mode="FORWARD" type="JSP">
		<RESOURCES>
			<ITEM prog="0" resource="/jsp/notificheRDC/esitoNucleoRDC.jsp"/>
		</RESOURCES>
	</RENDERING>
</PUBLISHER>

<PUBLISHER name="NotificheRDCRisultRicercaCsvPub">
    <RENDERING channel="HTTP" type="JSP" mode="FORWARD">
      <RESOURCES>
        <item prog="0" resource="/jsp/notificheRDC/NotificheRDCRisultRicercaCsv.jsp"/>
      </RESOURCES>
    </RENDERING>
</PUBLISHER>

<!-- Eventi condizionalità -->
<PUBLISHER name="EventoCondizionalitaPagePub">
    <RENDERING channel="HTTP" type="JSP" mode="FORWARD">
      <RESOURCES>
        <item prog="0" resource="/jsp/eventiCondizionalitaRDC/EventoCondizionalita.jsp"/>
      </RESOURCES>
    </RENDERING>
</PUBLISHER>
<PUBLISHER name="ListCondizionalitaPagePub">
    <RENDERING channel="HTTP" type="JSP" mode="FORWARD">
      <RESOURCES>
        <item prog="0" resource="/jsp/eventiCondizionalitaRDC/ListaEventi.jsp"/>
      </RESOURCES>
    </RENDERING>
</PUBLISHER>
<PUBLISHER name="DettaglioCondizionalitaPagePub">
    <RENDERING channel="HTTP" type="JSP" mode="FORWARD">
      <RESOURCES>
        <item prog="0" resource="/jsp/eventiCondizionalitaRDC/DettaglioEvento.jsp"/>
      </RESOURCES>
    </RENDERING>
</PUBLISHER>
<PUBLISHER name="RicercaDomandePagePub">
    <RENDERING channel="HTTP" type="JSP" mode="FORWARD">
      <RESOURCES>
        <item prog="0" resource="/jsp/eventiCondizionalitaRDC/ricercaDomandeLav.jsp"/>
      </RESOURCES>
    </RENDERING>
</PUBLISHER>
<PUBLISHER name="RicercaAzCondPagePub">
    <RENDERING channel="HTTP" type="JSP" mode="FORWARD">
      <RESOURCES>
        <item prog="0" resource="/jsp/eventiCondizionalitaRDC/ricercaAzioniLav.jsp"/>
      </RESOURCES>
    </RENDERING>
</PUBLISHER>
<PUBLISHER name="ElencoAzCondPagePub">
    <RENDERING channel="HTTP" type="JSP" mode="FORWARD">
      <RESOURCES>
        <item prog="0" resource="/jsp/eventiCondizionalitaRDC/esitoAzioniLav.jsp"/>
      </RESOURCES>
    </RENDERING>
</PUBLISHER>
<PUBLISHER name="ListaAzioniCondizionalitaPagePub">
    <RENDERING channel="HTTP" type="JSP" mode="FORWARD">
      <RESOURCES>
        <item prog="0" resource="/jsp/eventiCondizionalitaRDC/ListaAzioniCondizionalitaPage.jsp"/>
      </RESOURCES>
    </RENDERING>
</PUBLISHER>
<PUBLISHER name="RichiestaNucleoRDCPagePub">
    <RENDERING channel="HTTP" type="JSP" mode="FORWARD">
      <RESOURCES>
        <item prog="0" resource="/jsp/notificheRDC/ricercaNucleoRdc.jsp"/>
      </RESOURCES>
    </RENDERING>
</PUBLISHER>
<PUBLISHER name="StoricoNotificheRDCPagePub">
	<RENDERING channel="HTTP" mode="FORWARD" type="JSP">
		<RESOURCES>
			<ITEM prog="0" resource="/jsp/notificheRDC/storicoNotificheRDC.jsp"/>
		</RESOURCES>
	</RENDERING>
</PUBLISHER>
<PUBLISHER name="RicercaCondizionalitaPagePub">
    <RENDERING channel="HTTP" type="JSP" mode="FORWARD">
      <RESOURCES>
        <item prog="0" resource="/jsp/eventiCondizionalitaRDC/RicercaCondizionalita.jsp"/>
      </RESOURCES>
    </RENDERING>
</PUBLISHER>
<PUBLISHER name="ListaRicercaCondizionalitaPagePub">
    <RENDERING channel="HTTP" type="JSP" mode="FORWARD">
      <RESOURCES>
        <item prog="0" resource="/jsp/eventiCondizionalitaRDC/ListaRicercaCondizionalita.jsp"/>
      </RESOURCES>
    </RENDERING>
</PUBLISHER>
<PUBLISHER name="EventiCondRisultRicercaCsvPagePub">
    <RENDERING channel="HTTP" type="JSP" mode="FORWARD">
      <RESOURCES>
        <item prog="0" resource="/jsp/eventiCondizionalitaRDC/EventiCondizRisultRicercaCsv.jsp"/>
      </RESOURCES>
    </RENDERING>
</PUBLISHER>